src/elasticsearch7_mcp_server/__init__.py
src/elasticsearch7_mcp_server/es_client.py
src/elasticsearch7_mcp_server/server.py
orange_elasticsearch7_mcp_server-1.0.0.dist-info/METADATA
orange_elasticsearch7_mcp_server-1.0.0.dist-info/WHEEL
orange_elasticsearch7_mcp_server-1.0.0.dist-info/entry_points.txt
orange_elasticsearch7_mcp_server-1.0.0.dist-info/licenses/LICENSE
orange_elasticsearch7_mcp_server-1.0.0.dist-info/RECORD
